numberize/__init__.py
numberize/calculators.py
numberize/linguists.py
numberize/numberizer.py
numberize/replacers.py
numberize/tokenizers.py
numberize/dicts/__init__.py
numberize/dicts/en.py
numberize/dicts/ru.py
numberize/dicts/uk.py
numberize-1.1.2.dist-info/LICENSE
numberize-1.1.2.dist-info/METADATA
numberize-1.1.2.dist-info/WHEEL
numberize-1.1.2.dist-info/top_level.txt
numberize-1.1.2.dist-info/RECORD
