Metadata-Version: 2.1
Name: numberize
Version: 1.1.2
Summary: Replace numerals with numbers
Home-page: https://github.com/DanATW/numberize.git
Author: YemchenkoDS
Author-email: emchenko@dlit.dp.ua
Project-URL: Bug Tracker, https://github.com/DanATW/numberize/issues
Keywords: text replace numerals words numbers morphology
Classifier: Programming Language :: Python :: 3
Classifier: License :: OSI Approved :: MIT License
Classifier: Operating System :: OS Independent
Requires-Python: >=3.6
License-File: LICENSE
Requires-Dist: pymorphy3
Requires-Dist: pymorphy3-dicts-uk
Requires-Dist: nltk
